{
  "title": "PauseAI Bonn",
  "description": "Lokale Gruppe von PauseAI in Bonn — Wir setzen uns für sichere KI-Entwicklung und internationale Regulierung ein.",
  "lang": "de",
  "url": "",
  "nav": [
    { "label": "Events", "href": "#events" },
    { "label": "Links", "href": "#links" },
    { "label": "Über uns", "href": "#about" }
  ],
  "contact": [
    {
      "icon": "email",
      "label": "E-Mail",
      "value": "bonn@stopaigermany.de",
      "href": "mailto:bonn@stopaigermany.de"
    },
    {
      "icon": "discord",
      "label": "Discord",
      "value": "PauseAI Deutschland Server",
      "href": "https://discord.gg/pvZ5PmRX4R",
      "external": true
    },
    {
      "icon": "globe",
      "label": "Discord (International)",
      "value": "PauseAI Global Server",
      "href": "https://discord.gg/2XXWXvErfA",
      "external": true
    }
  ],
  "parentOrgs": [
    { "label": "PauseAI Deutschland", "url": "https://pause-ai.de" },
    { "label": "PauseAI Global", "url": "https://pauseai.info" }
  ]
}
